Metadata-Version: 2.1
Name: stencil-python-client
Version: 0.0.1
Summary: Stencil Python client package provides a store to lookup protobuf descriptors and options to keep the protobuf descriptors upto date.
Home-page: https://github.com/odpf/stencil
Author: ODPF
Author-email: odpf@gmail.com
License: UNKNOWN
Project-URL: Bug Tracker, https://github.com/odpf/stencil/issues
Platform: UNKNOWN
Classifier: Programming Language :: Python :: 3
Classifier: License :: OSI Approved :: Apache Software License
Classifier: Operating System :: OS Independent
Requires-Python: >=3.6
License-File: LICENSE
